ai_benchmark_analyzer/__init__.py
ai_benchmark_analyzer/main.py
ai_benchmark_analyzer/prompts.py
ai_benchmark_analyzer-2025.12.21193050.dist-info/METADATA
ai_benchmark_analyzer-2025.12.21193050.dist-info/WHEEL
ai_benchmark_analyzer-2025.12.21193050.dist-info/top_level.txt
ai_benchmark_analyzer-2025.12.21193050.dist-info/RECORD
