Metadata-Version: 2.4
Name: ai-benchmark-analyzer
Version: 2025.12.21193050
Summary: Analyzes and summarizes AI benchmark results from unstructured text descriptions.
Author-email: ai-benchmark-analyzer <hi@eugene.plus>
License: MIT
Project-URL: Homepage, https://github.com/chigwell/ai-benchmark-analyzer
Requires-Python: >=3.9
Requires-Dist: langchain-llm7>=0.0.0
Requires-Dist: llmatch-messages>=0.0.0
Requires-Dist: langchain-core>=0.3.0
